{
  "total_count": 194,
  "incomplete_results": false,
  "items": [
    {
      "url": "https://api.github.com/repos/yaph/d3-geomap/issues/51",
      "repository_url": "https://api.github.com/repos/yaph/d3-geomap",
      "labels_url": "https://api.github.com/repos/yaph/d3-geomap/issues/51/labels{/name}",
      "comments_url": "https://api.github.com/repos/yaph/d3-geomap/issues/51/comments",
      "events_url": "https://api.github.com/repos/yaph/d3-geomap/issues/51/events",
      "html_url": "https://github.com/yaph/d3-geomap/pull/51",
      "id": 440900169,
      "node_id": "MDExOlB1bGxSZXF1ZXN0Mjc2MzQ1Nzc3",
      "number": 51,
      "title": "feat: build standard d3-module for d3v4+ & update examples",
      "user": {
        "login": "dpraul",
        "id": 931325,
        "node_id": "MDQ6VXNlcjkzMTMyNQ==",
        "avatar_url": "https://avatars0.githubusercontent.com/u/931325?v=4",
        "gravatar_id": "",
        "url": "https://api.github.com/users/dpraul",
        "html_url": "https://github.com/dpraul",
        "followers_url": "https://api.github.com/users/dpraul/followers",
        "following_url": "https://api.github.com/users/dpraul/following{/other_user}",
        "gists_url": "https://api.github.com/users/dpraul/gists{/gist_id}",
        "starred_url": "https://api.github.com/users/dpraul/starred{/owner}{/repo}",
        "subscriptions_url": "https://api.github.com/users/dpraul/subscriptions",
        "organizations_url": "https://api.github.com/users/dpraul/orgs",
        "repos_url": "https://api.github.com/users/dpraul/repos",
        "events_url": "https://api.github.com/users/dpraul/events{/privacy}",
        "received_events_url": "https://api.github.com/users/dpraul/received_events",
        "type": "User",
        "site_admin": false
      },
      "labels": [

      ],
      "state": "open",
      "locked": false,
      "assignee": null,
      "assignees": [

      ],
      "milestone": null,
      "comments": 1,
      "created_at": "2019-05-06T21:22:25Z",
      "updated_at": "2019-05-10T10:11:12Z",
      "closed_at": null,
      "author_association": "NONE",
      "pull_request": {
        "url": "https://api.github.com/repos/yaph/d3-geomap/pulls/51",
        "html_url": "https://github.com/yaph/d3-geomap/pull/51",
        "diff_url": "https://github.com/yaph/d3-geomap/pull/51.diff",
        "patch_url": "https://github.com/yaph/d3-geomap/pull/51.patch"
      },
      "body": "With the release of version 4, `d3` moved over to a modular approach, wherein everything is a plugin that extends off the main `d3` module. In doing so, they setup [a standard approach to building `d3` modules](https://bost.ocks.org/mike/d3-plugin/). I originally recommended `webpack` for bundling source code, but the rest of the `d3` universe uses [rollup](https://rollupjs.org) with a standard configuration (example for [`d3-shape`](https://github.com/d3/d3-shape/blob/master/rollup.config.js)).\r\n\r\nSummarized, a standard d3-module for v4+ entails:\r\n - using the standard rollup config\r\n - filename outputs to `d3-geomap` (instead of `d3.geomap`)\r\n - requiring individual packages instead of d3's main package\r\n\r\nFor convenience, I've added the following:\r\n - use `rollup-plugin-babel` to transpile ES6\r\n - use `rollup-plugin-postcss` to compile sass\r\n - serve examples using `rollup-plugin-serve`\r\n - remove dependency on `d3-geo-projection` (user can load if needed - the default projection is available in `d3-geo`)\r\n - wrap CSS styles in `d3-geomap` class to not styles to global DOM, e.g. `<text>`\r\n\r\nI've made several other small changes around the edges that I am happy to explain if you're wondering why they were made.\r\n\r\nBelow are the breaking changes. Do note, the API does not need to be changed, but I think making each of the exports distinct calls really clears up usage.\r\n\r\nBREAKING CHANGES:\r\n - files outputs are now:\r\n   - `dist/d3-geomap.js` and `dist/d3-geomap.min.js`\r\n   - `dist/d3-geomap.css` and `dist/d3-geomap.min.css`\r\n - API is now `d3.geomap()`, `d3.choropleth()`, and `d3.colorbrewer()`\r\n - `d3-geomap` class must be added to map elements for default styling",
      "score": 1.0
    },
    {
      "url": "https://api.github.com/repos/yaph/d3-geomap/issues/49",
      "repository_url": "https://api.github.com/repos/yaph/d3-geomap",
      "labels_url": "https://api.github.com/repos/yaph/d3-geomap/issues/49/labels{/name}",
      "comments_url": "https://api.github.com/repos/yaph/d3-geomap/issues/49/comments",
      "events_url": "https://api.github.com/repos/yaph/d3-geomap/issues/49/events",
      "html_url": "https://github.com/yaph/d3-geomap/issues/49",
      "id": 420164634,
      "node_id": "MDU6SXNzdWU0MjAxNjQ2MzQ=",
      "number": 49,
      "title": "No distributable provided for import/require",
      "user": {
        "login": "dpraul",
        "id": 931325,
        "node_id": "MDQ6VXNlcjkzMTMyNQ==",
        "avatar_url": "https://avatars0.githubusercontent.com/u/931325?v=4",
        "gravatar_id": "",
        "url": "https://api.github.com/users/dpraul",
        "html_url": "https://github.com/dpraul",
        "followers_url": "https://api.github.com/users/dpraul/followers",
        "following_url": "https://api.github.com/users/dpraul/following{/other_user}",
        "gists_url": "https://api.github.com/users/dpraul/gists{/gist_id}",
        "starred_url": "https://api.github.com/users/dpraul/starred{/owner}{/repo}",
        "subscriptions_url": "https://api.github.com/users/dpraul/subscriptions",
        "organizations_url": "https://api.github.com/users/dpraul/orgs",
        "repos_url": "https://api.github.com/users/dpraul/repos",
        "events_url": "https://api.github.com/users/dpraul/events{/privacy}",
        "received_events_url": "https://api.github.com/users/dpraul/received_events",
        "type": "User",
        "site_admin": false
      },
      "labels": [
        {
          "id": 92603628,
          "node_id": "MDU6TGFiZWw5MjYwMzYyOA==",
          "url": "https://api.github.com/repos/yaph/d3-geomap/labels/help%20wanted",
          "name": "help wanted",
          "color": "159818",
          "default": true
        }
      ],
      "state": "open",
      "locked": false,
      "assignee": null,
      "assignees": [

      ],
      "milestone": null,
      "comments": 6,
      "created_at": "2019-03-12T19:23:50Z",
      "updated_at": "2019-05-07T13:10:57Z",
      "closed_at": null,
      "author_association": "NONE",
      "body": "Usually, a library delivered over npm provides a built version that another module can directly consume with `import` or `require`. This is usually done by pointing [`main` in `package.json`](https://docs.npmjs.com/files/package.json#main) to a file within the source bundle. If I'm understanding #44, this is the same problem they are facing - although `jsDelivr` is not a standard key in `package.json` so is not the proper solution.\r\n\r\nTo fix this, either (a) the distributable needs to be included in the source bundle uploaded to `npm`, (b) the package needs to be built by import/require instead of concatenation, or - ideally - (c) both!\r\n\r\n(a) is the easiest and requires the least restructuring, and the simplicity of this library means (b) probably isn't too far off as well. If you're looking for assistance, happy to make a PR (although it may seem drastic)",
      "score": 1.0
    },
    {
      "url": "https://api.github.com/repos/yaph/d3-geomap/issues/50",
      "repository_url": "https://api.github.com/repos/yaph/d3-geomap",
      "labels_url": "https://api.github.com/repos/yaph/d3-geomap/issues/50/labels{/name}",
      "comments_url": "https://api.github.com/repos/yaph/d3-geomap/issues/50/comments",
      "events_url": "https://api.github.com/repos/yaph/d3-geomap/issues/50/events",
      "html_url": "https://github.com/yaph/d3-geomap/issues/50",
      "id": 438614974,
      "node_id": "MDU6SXNzdWU0Mzg2MTQ5NzQ=",
      "number": 50,
      "title": "RTL support for d3 geomap - choropleth",
      "user": {
        "login": "pavandixit93",
        "id": 21095558,
        "node_id": "MDQ6VXNlcjIxMDk1NTU4",
        "avatar_url": "https://avatars1.githubusercontent.com/u/21095558?v=4",
        "gravatar_id": "",
        "url": "https://api.github.com/users/pavandixit93",
        "html_url": "https://github.com/pavandixit93",
        "followers_url": "https://api.github.com/users/pavandixit93/followers",
        "following_url": "https://api.github.com/users/pavandixit93/following{/other_user}",
        "gists_url": "https://api.github.com/users/pavandixit93/gists{/gist_id}",
        "starred_url": "https://api.github.com/users/pavandixit93/starred{/owner}{/repo}",
        "subscriptions_url": "https://api.github.com/users/pavandixit93/subscriptions",
        "organizations_url": "https://api.github.com/users/pavandixit93/orgs",
        "repos_url": "https://api.github.com/users/pavandixit93/repos",
        "events_url": "https://api.github.com/users/pavandixit93/events{/privacy}",
        "received_events_url": "https://api.github.com/users/pavandixit93/received_events",
        "type": "User",
        "site_admin": false
      },
      "labels": [
        {
          "id": 92603628,
          "node_id": "MDU6TGFiZWw5MjYwMzYyOA==",
          "url": "https://api.github.com/repos/yaph/d3-geomap/labels/help%20wanted",
          "name": "help wanted",
          "color": "159818",
          "default": true
        }
      ],
      "state": "open",
      "locked": false,
      "assignee": null,
      "assignees": [

      ],
      "milestone": null,
      "comments": 1,
      "created_at": "2019-04-30T06:02:17Z",
      "updated_at": "2019-05-04T06:36:24Z",
      "closed_at": null,
      "author_association": "NONE",
      "body": "When i try to add dir=\"rtl\" in HTML tag, As per observation d3 geomap does not have RTL processing, Is there any RTL related config or how to add RTL support in D3 geomap library?",
      "score": 1.0
    },
    {
      "url": "https://api.github.com/repos/yaph/d3-geomap/issues/44",
      "repository_url": "https://api.github.com/repos/yaph/d3-geomap",
      "labels_url": "https://api.github.com/repos/yaph/d3-geomap/issues/44/labels{/name}",
      "comments_url": "https://api.github.com/repos/yaph/d3-geomap/issues/44/comments",
      "events_url": "https://api.github.com/repos/yaph/d3-geomap/issues/44/events",
      "html_url": "https://github.com/yaph/d3-geomap/issues/44",
      "id": 279903570,
      "node_id": "MDU6SXNzdWUyNzk5MDM1NzA=",
      "number": 44,
      "title": "No default jsDelivr CDN file set",
      "user": {
        "login": "szafirov",
        "id": 5066348,
        "node_id": "MDQ6VXNlcjUwNjYzNDg=",
        "avatar_url": "https://avatars2.githubusercontent.com/u/5066348?v=4",
        "gravatar_id": "",
        "url": "https://api.github.com/users/szafirov",
        "html_url": "https://github.com/szafirov",
        "followers_url": "https://api.github.com/users/szafirov/followers",
        "following_url": "https://api.github.com/users/szafirov/following{/other_user}",
        "gists_url": "https://api.github.com/users/szafirov/gists{/gist_id}",
        "starred_url": "https://api.github.com/users/szafirov/starred{/owner}{/repo}",
        "subscriptions_url": "https://api.github.com/users/szafirov/subscriptions",
        "organizations_url": "https://api.github.com/users/szafirov/orgs",
        "repos_url": "https://api.github.com/users/szafirov/repos",
        "events_url": "https://api.github.com/users/szafirov/events{/privacy}",
        "received_events_url": "https://api.github.com/users/szafirov/received_events",
        "type": "User",
        "site_admin": false
      },
      "labels": [
        {
          "id": 92603628,
          "node_id": "MDU6TGFiZWw5MjYwMzYyOA==",
          "url": "https://api.github.com/repos/yaph/d3-geomap/labels/help%20wanted",
          "name": "help wanted",
          "color": "159818",
          "default": true
        }
      ],
      "state": "open",
      "locked": false,
      "assignee": null,
      "assignees": [

      ],
      "milestone": null,
      "comments": 3,
      "created_at": "2017-12-06T20:57:04Z",
      "updated_at": "2019-05-04T06:36:23Z",
      "closed_at": null,
      "author_association": "NONE",
      "body": "[This package](https://www.jsdelivr.com/package/npm/d3-geomap) doesn't have a [default file](https://www.jsdelivr.com/features#publishing-packages) set. You can set it via `jsdelivr`, `browser`, or `main` field in `package.json`",
      "score": 1.0
    },
    {
      "url": "https://api.github.com/repos/yaph/d3-geomap/issues/47",
      "repository_url": "https://api.github.com/repos/yaph/d3-geomap",
      "labels_url": "https://api.github.com/repos/yaph/d3-geomap/issues/47/labels{/name}",
      "comments_url": "https://api.github.com/repos/yaph/d3-geomap/issues/47/comments",
      "events_url": "https://api.github.com/repos/yaph/d3-geomap/issues/47/events",
      "html_url": "https://github.com/yaph/d3-geomap/issues/47",
      "id": 374534549,
      "node_id": "MDU6SXNzdWUzNzQ1MzQ1NDk=",
      "number": 47,
      "title": "How to use this library with typescript or any other module loaders? ",
      "user": {
        "login": "vinayakpatil",
        "id": 3096223,
        "node_id": "MDQ6VXNlcjMwOTYyMjM=",
        "avatar_url": "https://avatars0.githubusercontent.com/u/3096223?v=4",
        "gravatar_id": "",
        "url": "https://api.github.com/users/vinayakpatil",
        "html_url": "https://github.com/vinayakpatil",
        "followers_url": "https://api.github.com/users/vinayakpatil/followers",
        "following_url": "https://api.github.com/users/vinayakpatil/following{/other_user}",
        "gists_url": "https://api.github.com/users/vinayakpatil/gists{/gist_id}",
        "starred_url": "https://api.github.com/users/vinayakpatil/starred{/owner}{/repo}",
        "subscriptions_url": "https://api.github.com/users/vinayakpatil/subscriptions",
        "organizations_url": "https://api.github.com/users/vinayakpatil/orgs",
        "repos_url": "https://api.github.com/users/vinayakpatil/repos",
        "events_url": "https://api.github.com/users/vinayakpatil/events{/privacy}",
        "received_events_url": "https://api.github.com/users/vinayakpatil/received_events",
        "type": "User",
        "site_admin": false
      },
      "labels": [

      ],
      "state": "closed",
      "locked": false,
      "assignee": null,
      "assignees": [

      ],
      "milestone": null,
      "comments": 1,
      "created_at": "2018-10-26T20:22:28Z",
      "updated_at": "2019-02-23T22:05:14Z",
      "closed_at": "2019-02-23T22:05:14Z",
      "author_association": "NONE",
      "body": "Currently, its difficult to integrate this library with angular project. Neither this is compatible with module bundlers not there is a dist/build folder part of this repo. ",
      "score": 1.0
    },
    {
      "url": "https://api.github.com/repos/yaph/d3-geomap/issues/48",
      "repository_url": "https://api.github.com/repos/yaph/d3-geomap",
      "labels_url": "https://api.github.com/repos/yaph/d3-geomap/issues/48/labels{/name}",
      "comments_url": "https://api.github.com/repos/yaph/d3-geomap/issues/48/comments",
      "events_url": "https://api.github.com/repos/yaph/d3-geomap/issues/48/events",
      "html_url": "https://github.com/yaph/d3-geomap/issues/48",
      "id": 409232466,
      "node_id": "MDU6SXNzdWU0MDkyMzI0NjY=",
      "number": 48,
      "title": "Custom marker support",
      "user": {
        "login": "vinayakpatil",
        "id": 3096223,
        "node_id": "MDQ6VXNlcjMwOTYyMjM=",
        "avatar_url": "https://avatars0.githubusercontent.com/u/3096223?v=4",
        "gravatar_id": "",
        "url": "https://api.github.com/users/vinayakpatil",
        "html_url": "https://github.com/vinayakpatil",
        "followers_url": "https://api.github.com/users/vinayakpatil/followers",
        "following_url": "https://api.github.com/users/vinayakpatil/following{/other_user}",
        "gists_url": "https://api.github.com/users/vinayakpatil/gists{/gist_id}",
        "starred_url": "https://api.github.com/users/vinayakpatil/starred{/owner}{/repo}",
        "subscriptions_url": "https://api.github.com/users/vinayakpatil/subscriptions",
        "organizations_url": "https://api.github.com/users/vinayakpatil/orgs",
        "repos_url": "https://api.github.com/users/vinayakpatil/repos",
        "events_url": "https://api.github.com/users/vinayakpatil/events{/privacy}",
        "received_events_url": "https://api.github.com/users/vinayakpatil/received_events",
        "type": "User",
        "site_admin": false
      },
      "labels": [

      ],
      "state": "closed",
      "locked": false,
      "assignee": null,
      "assignees": [

      ],
      "milestone": null,
      "comments": 1,
      "created_at": "2019-02-12T10:42:43Z",
      "updated_at": "2019-02-15T23:41:51Z",
      "closed_at": "2019-02-15T23:41:51Z",
      "author_association": "NONE",
      "body": "![image](https://user-images.githubusercontent.com/3096223/52629979-f46f5600-2ee0-11e9-89d6-92a0b4aa3e31.png)\r\n\r\nIs there any way to visualize with custom country markers?",
      "score": 1.0
    },
    {
      "url": "https://api.github.com/repos/yaph/logya/issues/83",
      "repository_url": "https://api.github.com/repos/yaph/logya",
      "labels_url": "https://api.github.com/repos/yaph/logya/issues/83/labels{/name}",
      "comments_url": "https://api.github.com/repos/yaph/logya/issues/83/comments",
      "events_url": "https://api.github.com/repos/yaph/logya/issues/83/events",
      "html_url": "https://github.com/yaph/logya/issues/83",
      "id": 402492424,
      "node_id": "MDU6SXNzdWU0MDI0OTI0MjQ=",
      "number": 83,
      "title": "Create an index database that is read and updated in serve mode",
      "user": {
        "login": "yaph",
        "id": 60051,
        "node_id": "MDQ6VXNlcjYwMDUx",
        "avatar_url": "https://avatars3.githubusercontent.com/u/60051?v=4",
        "gravatar_id": "",
        "url": "https://api.github.com/users/yaph",
        "html_url": "https://github.com/yaph",
        "followers_url": "https://api.github.com/users/yaph/followers",
        "following_url": "https://api.github.com/users/yaph/following{/other_user}",
        "gists_url": "https://api.github.com/users/yaph/gists{/gist_id}",
        "starred_url": "https://api.github.com/users/yaph/starred{/owner}{/repo}",
        "subscriptions_url": "https://api.github.com/users/yaph/subscriptions",
        "organizations_url": "https://api.github.com/users/yaph/orgs",
        "repos_url": "https://api.github.com/users/yaph/repos",
        "events_url": "https://api.github.com/users/yaph/events{/privacy}",
        "received_events_url": "https://api.github.com/users/yaph/received_events",
        "type": "User",
        "site_admin": false
      },
      "labels": [

      ],
      "state": "open",
      "locked": false,
      "assignee": null,
      "assignees": [

      ],
      "milestone": {
        "url": "https://api.github.com/repos/yaph/logya/milestones/5",
        "html_url": "https://github.com/yaph/logya/milestone/5",
        "labels_url": "https://api.github.com/repos/yaph/logya/milestones/5/labels",
        "id": 1107505,
        "node_id": "MDk6TWlsZXN0b25lMTEwNzUwNQ==",
        "number": 5,
        "title": "Better Document Index",
        "description": "",
        "creator": {
          "login": "yaph",
          "id": 60051,
          "node_id": "MDQ6VXNlcjYwMDUx",
          "avatar_url": "https://avatars3.githubusercontent.com/u/60051?v=4",
          "gravatar_id": "",
          "url": "https://api.github.com/users/yaph",
          "html_url": "https://github.com/yaph",
          "followers_url": "https://api.github.com/users/yaph/followers",
          "following_url": "https://api.github.com/users/yaph/following{/other_user}",
          "gists_url": "https://api.github.com/users/yaph/gists{/gist_id}",
          "starred_url": "https://api.github.com/users/yaph/starred{/owner}{/repo}",
          "subscriptions_url": "https://api.github.com/users/yaph/subscriptions",
          "organizations_url": "https://api.github.com/users/yaph/orgs",
          "repos_url": "https://api.github.com/users/yaph/repos",
          "events_url": "https://api.github.com/users/yaph/events{/privacy}",
          "received_events_url": "https://api.github.com/users/yaph/received_events",
          "type": "User",
          "site_admin": false
        },
        "open_issues": 5,
        "closed_issues": 5,
        "state": "open",
        "created_at": "2015-05-12T20:31:55Z",
        "updated_at": "2019-01-24T00:40:46Z",
        "due_on": null,
        "closed_at": null
      },
      "comments": 0,
      "created_at": "2019-01-24T00:40:46Z",
      "updated_at": "2019-01-24T00:40:46Z",
      "closed_at": null,
      "author_association": "OWNER",
      "body": "When creating a site by sub-classing generate, indexes for pages not present in content are not generated.\r\n\r\nWhat a document index could look like:\r\n\r\n    index = {\r\n        '/about/': {'file': 'about.md'},\r\n        '/dynamic-file/': {'doc': {'title': 'Document generated from different source.'}}\r\n    }\r\n\r\nThe keys are the canonical document URLs without the host. For files existing in the ``content`` directory, only store the filename. For other data sources store the complete document.\r\n\r\nThis index is created in the ``generate`` step and read in ``serve`` mode.\r\n\r\n## Questions\r\n\r\n* Can it be avoided to call ``build_index()`` on every page request?\r\n* How will new ``content`` documents be added to the index in serve mode?",
      "score": 1.0
    },
    {
      "url": "https://api.github.com/repos/yaph/d3-geomap/issues/42",
      "repository_url": "https://api.github.com/repos/yaph/d3-geomap",
      "labels_url": "https://api.github.com/repos/yaph/d3-geomap/issues/42/labels{/name}",
      "comments_url": "https://api.github.com/repos/yaph/d3-geomap/issues/42/comments",
      "events_url": "https://api.github.com/repos/yaph/d3-geomap/issues/42/events",
      "html_url": "https://github.com/yaph/d3-geomap/issues/42",
      "id": 232054798,
      "node_id": "MDU6SXNzdWUyMzIwNTQ3OTg=",
      "number": 42,
      "title": "Update docs with new draw worklfow",
      "user": {
        "login": "yaph",
        "id": 60051,
        "node_id": "MDQ6VXNlcjYwMDUx",
        "avatar_url": "https://avatars3.githubusercontent.com/u/60051?v=4",
        "gravatar_id": "",
        "url": "https://api.github.com/users/yaph",
        "html_url": "https://github.com/yaph",
        "followers_url": "https://api.github.com/users/yaph/followers",
        "following_url": "https://api.github.com/users/yaph/following{/other_user}",
        "gists_url": "https://api.github.com/users/yaph/gists{/gist_id}",
        "starred_url": "https://api.github.com/users/yaph/starred{/owner}{/repo}",
        "subscriptions_url": "https://api.github.com/users/yaph/subscriptions",
        "organizations_url": "https://api.github.com/users/yaph/orgs",
        "repos_url": "https://api.github.com/users/yaph/repos",
        "events_url": "https://api.github.com/users/yaph/events{/privacy}",
        "received_events_url": "https://api.github.com/users/yaph/received_events",
        "type": "User",
        "site_admin": false
      },
      "labels": [

      ],
      "state": "closed",
      "locked": false,
      "assignee": null,
      "assignees": [

      ],
      "milestone": {
        "url": "https://api.github.com/repos/yaph/d3-geomap/milestones/1",
        "html_url": "https://github.com/yaph/d3-geomap/milestone/1",
        "labels_url": "https://api.github.com/repos/yaph/d3-geomap/milestones/1/labels",
        "id": 2548765,
        "node_id": "MDk6TWlsZXN0b25lMjU0ODc2NQ==",
        "number": 1,
        "title": "v2",
        "description": null,
        "creator": {
          "login": "yaph",
          "id": 60051,
          "node_id": "MDQ6VXNlcjYwMDUx",
          "avatar_url": "https://avatars3.githubusercontent.com/u/60051?v=4",
          "gravatar_id": "",
          "url": "https://api.github.com/users/yaph",
          "html_url": "https://github.com/yaph",
          "followers_url": "https://api.github.com/users/yaph/followers",
          "following_url": "https://api.github.com/users/yaph/following{/other_user}",
          "gists_url": "https://api.github.com/users/yaph/gists{/gist_id}",
          "starred_url": "https://api.github.com/users/yaph/starred{/owner}{/repo}",
          "subscriptions_url": "https://api.github.com/users/yaph/subscriptions",
          "organizations_url": "https://api.github.com/users/yaph/orgs",
          "repos_url": "https://api.github.com/users/yaph/repos",
          "events_url": "https://api.github.com/users/yaph/events{/privacy}",
          "received_events_url": "https://api.github.com/users/yaph/received_events",
          "type": "User",
          "site_admin": false
        },
        "open_issues": 0,
        "closed_issues": 3,
        "state": "open",
        "created_at": "2017-05-29T15:46:35Z",
        "updated_at": "2018-10-19T22:42:10Z",
        "due_on": null,
        "closed_at": null
      },
      "comments": 1,
      "created_at": "2017-05-29T15:46:15Z",
      "updated_at": "2018-10-19T22:42:10Z",
      "closed_at": "2018-10-19T22:42:10Z",
      "author_association": "OWNER",
      "body": "",
      "score": 1.0
    },
    {
      "url": "https://api.github.com/repos/yaph/d3-geomap/issues/28",
      "repository_url": "https://api.github.com/repos/yaph/d3-geomap",
      "labels_url": "https://api.github.com/repos/yaph/d3-geomap/issues/28/labels{/name}",
      "comments_url": "https://api.github.com/repos/yaph/d3-geomap/issues/28/comments",
      "events_url": "https://api.github.com/repos/yaph/d3-geomap/issues/28/events",
      "html_url": "https://github.com/yaph/d3-geomap/issues/28",
      "id": 46168454,
      "node_id": "MDU6SXNzdWU0NjE2ODQ1NA==",
      "number": 28,
      "title": "Find a way to indicate disputed territories",
      "user": {
        "login": "yaph",
        "id": 60051,
        "node_id": "MDQ6VXNlcjYwMDUx",
        "avatar_url": "https://avatars3.githubusercontent.com/u/60051?v=4",
        "gravatar_id": "",
        "url": "https://api.github.com/users/yaph",
        "html_url": "https://github.com/yaph",
        "followers_url": "https://api.github.com/users/yaph/followers",
        "following_url": "https://api.github.com/users/yaph/following{/other_user}",
        "gists_url": "https://api.github.com/users/yaph/gists{/gist_id}",
        "starred_url": "https://api.github.com/users/yaph/starred{/owner}{/repo}",
        "subscriptions_url": "https://api.github.com/users/yaph/subscriptions",
        "organizations_url": "https://api.github.com/users/yaph/orgs",
        "repos_url": "https://api.github.com/users/yaph/repos",
        "events_url": "https://api.github.com/users/yaph/events{/privacy}",
        "received_events_url": "https://api.github.com/users/yaph/received_events",
        "type": "User",
        "site_admin": false
      },
      "labels": [
        {
          "id": 92603627,
          "node_id": "MDU6TGFiZWw5MjYwMzYyNw==",
          "url": "https://api.github.com/repos/yaph/d3-geomap/labels/enhancement",
          "name": "enhancement",
          "color": "84b6eb",
          "default": true
        }
      ],
      "state": "closed",
      "locked": false,
      "assignee": null,
      "assignees": [

      ],
      "milestone": null,
      "comments": 1,
      "created_at": "2014-10-18T09:06:10Z",
      "updated_at": "2018-10-19T20:34:42Z",
      "closed_at": "2018-10-19T20:34:42Z",
      "author_association": "OWNER",
      "body": "http://en.wikipedia.org/wiki/List_of_states_with_limited_recognition\n\nUsing diagonal stripes as an SVG background pattern might work. Dashed borders would not work, because topojson eliminates redundancy of boundary lines.\n",
      "score": 1.0
    },
    {
      "url": "https://api.github.com/repos/yaph/d3-geomap/issues/43",
      "repository_url": "https://api.github.com/repos/yaph/d3-geomap",
      "labels_url": "https://api.github.com/repos/yaph/d3-geomap/issues/43/labels{/name}",
      "comments_url": "https://api.github.com/repos/yaph/d3-geomap/issues/43/comments",
      "events_url": "https://api.github.com/repos/yaph/d3-geomap/issues/43/events",
      "html_url": "https://github.com/yaph/d3-geomap/issues/43",
      "id": 232364309,
      "node_id": "MDU6SXNzdWUyMzIzNjQzMDk=",
      "number": 43,
      "title": "v2.0.0alpha doesn't work on iOS",
      "user": {
        "login": "yaph",
        "id": 60051,
        "node_id": "MDQ6VXNlcjYwMDUx",
        "avatar_url": "https://avatars3.githubusercontent.com/u/60051?v=4",
        "gravatar_id": "",
        "url": "https://api.github.com/users/yaph",
        "html_url": "https://github.com/yaph",
        "followers_url": "https://api.github.com/users/yaph/followers",
        "following_url": "https://api.github.com/users/yaph/following{/other_user}",
        "gists_url": "https://api.github.com/users/yaph/gists{/gist_id}",
        "starred_url": "https://api.github.com/users/yaph/starred{/owner}{/repo}",
        "subscriptions_url": "https://api.github.com/users/yaph/subscriptions",
        "organizations_url": "https://api.github.com/users/yaph/orgs",
        "repos_url": "https://api.github.com/users/yaph/repos",
        "events_url": "https://api.github.com/users/yaph/events{/privacy}",
        "received_events_url": "https://api.github.com/users/yaph/received_events",
        "type": "User",
        "site_admin": false
      },
      "labels": [
        {
          "id": 92603625,
          "node_id": "MDU6TGFiZWw5MjYwMzYyNQ==",
          "url": "https://api.github.com/repos/yaph/d3-geomap/labels/bug",
          "name": "bug",
          "color": "fc2929",
          "default": true
        }
      ],
      "state": "closed",
      "locked": false,
      "assignee": null,
      "assignees": [

      ],
      "milestone": {
        "url": "https://api.github.com/repos/yaph/d3-geomap/milestones/1",
        "html_url": "https://github.com/yaph/d3-geomap/milestone/1",
        "labels_url": "https://api.github.com/repos/yaph/d3-geomap/milestones/1/labels",
        "id": 2548765,
        "node_id": "MDk6TWlsZXN0b25lMjU0ODc2NQ==",
        "number": 1,
        "title": "v2",
        "description": null,
        "creator": {
          "login": "yaph",
          "id": 60051,
          "node_id": "MDQ6VXNlcjYwMDUx",
          "avatar_url": "https://avatars3.githubusercontent.com/u/60051?v=4",
          "gravatar_id": "",
          "url": "https://api.github.com/users/yaph",
          "html_url": "https://github.com/yaph",
          "followers_url": "https://api.github.com/users/yaph/followers",
          "following_url": "https://api.github.com/users/yaph/following{/other_user}",
          "gists_url": "https://api.github.com/users/yaph/gists{/gist_id}",
          "starred_url": "https://api.github.com/users/yaph/starred{/owner}{/repo}",
          "subscriptions_url": "https://api.github.com/users/yaph/subscriptions",
          "organizations_url": "https://api.github.com/users/yaph/orgs",
          "repos_url": "https://api.github.com/users/yaph/repos",
          "events_url": "https://api.github.com/users/yaph/events{/privacy}",
          "received_events_url": "https://api.github.com/users/yaph/received_events",
          "type": "User",
          "site_admin": false
        },
        "open_issues": 0,
        "closed_issues": 3,
        "state": "open",
        "created_at": "2017-05-29T15:46:35Z",
        "updated_at": "2018-10-19T22:42:10Z",
        "due_on": null,
        "closed_at": null
      },
      "comments": 2,
      "created_at": "2017-05-30T19:58:51Z",
      "updated_at": "2018-10-19T20:26:18Z",
      "closed_at": "2018-10-19T20:26:18Z",
      "author_association": "OWNER",
      "body": "Remote debugging via https://jsconsole.com/ only produced `:0 Script error.` as output. Other debugging methods all seem to require OSX.",
      "score": 1.0
    },
    {
      "url": "https://api.github.com/repos/yaph/d3-geomap/issues/46",
      "repository_url": "https://api.github.com/repos/yaph/d3-geomap",
      "labels_url": "https://api.github.com/repos/yaph/d3-geomap/issues/46/labels{/name}",
      "comments_url": "https://api.github.com/repos/yaph/d3-geomap/issues/46/comments",
      "events_url": "https://api.github.com/repos/yaph/d3-geomap/issues/46/events",
      "html_url": "https://github.com/yaph/d3-geomap/issues/46",
      "id": 371946904,
      "node_id": "MDU6SXNzdWUzNzE5NDY5MDQ=",
      "number": 46,
      "title": "Uncaught TypeError: d[self.properties.column].trim is not a function",
      "user": {
        "login": "jendamozna",
        "id": 19552944,
        "node_id": "MDQ6VXNlcjE5NTUyOTQ0",
        "avatar_url": "https://avatars1.githubusercontent.com/u/19552944?v=4",
        "gravatar_id": "",
        "url": "https://api.github.com/users/jendamozna",
        "html_url": "https://github.com/jendamozna",
        "followers_url": "https://api.github.com/users/jendamozna/followers",
        "following_url": "https://api.github.com/users/jendamozna/following{/other_user}",
        "gists_url": "https://api.github.com/users/jendamozna/gists{/gist_id}",
        "starred_url": "https://api.github.com/users/jendamozna/starred{/owner}{/repo}",
        "subscriptions_url": "https://api.github.com/users/jendamozna/subscriptions",
        "organizations_url": "https://api.github.com/users/jendamozna/orgs",
        "repos_url": "https://api.github.com/users/jendamozna/repos",
        "events_url": "https://api.github.com/users/jendamozna/events{/privacy}",
        "received_events_url": "https://api.github.com/users/jendamozna/received_events",
        "type": "User",
        "site_admin": false
      },
      "labels": [

      ],
      "state": "closed",
      "locked": false,
      "assignee": null,
      "assignees": [

      ],
      "milestone": null,
      "comments": 1,
      "created_at": "2018-10-19T12:58:55Z",
      "updated_at": "2018-10-19T20:10:02Z",
      "closed_at": "2018-10-19T20:10:02Z",
      "author_association": "NONE",
      "body": "when called with array:\r\n\r\n.datum([ {iso3: \"RUS\", Requests: 10}])\r\n\r\nThe trim() method cant be applied on integer:\r\nd3.geomap.js:491\r\nval = d[self.properties.column].trim();",
      "score": 1.0
    },
    {
      "url": "https://api.github.com/repos/yaph/geonamescache/issues/18",
      "repository_url": "https://api.github.com/repos/yaph/geonamescache",
      "labels_url": "https://api.github.com/repos/yaph/geonamescache/issues/18/labels{/name}",
      "comments_url": "https://api.github.com/repos/yaph/geonamescache/issues/18/comments",
      "events_url": "https://api.github.com/repos/yaph/geonamescache/issues/18/events",
      "html_url": "https://github.com/yaph/geonamescache/issues/18",
      "id": 264156864,
      "node_id": "MDU6SXNzdWUyNjQxNTY4NjQ=",
      "number": 18,
      "title": "Update to latest geonames data",
      "user": {
        "login": "mcarans",
        "id": 3799212,
        "node_id": "MDQ6VXNlcjM3OTkyMTI=",
        "avatar_url": "https://avatars3.githubusercontent.com/u/3799212?v=4",
        "gravatar_id": "",
        "url": "https://api.github.com/users/mcarans",
        "html_url": "https://github.com/mcarans",
        "followers_url": "https://api.github.com/users/mcarans/followers",
        "following_url": "https://api.github.com/users/mcarans/following{/other_user}",
        "gists_url": "https://api.github.com/users/mcarans/gists{/gist_id}",
        "starred_url": "https://api.github.com/users/mcarans/starred{/owner}{/repo}",
        "subscriptions_url": "https://api.github.com/users/mcarans/subscriptions",
        "organizations_url": "https://api.github.com/users/mcarans/orgs",
        "repos_url": "https://api.github.com/users/mcarans/repos",
        "events_url": "https://api.github.com/users/mcarans/events{/privacy}",
        "received_events_url": "https://api.github.com/users/mcarans/received_events",
        "type": "User",
        "site_admin": false
      },
      "labels": [

      ],
      "state": "closed",
      "locked": false,
      "assignee": null,
      "assignees": [

      ],
      "milestone": null,
      "comments": 4,
      "created_at": "2017-10-10T09:24:22Z",
      "updated_at": "2018-05-18T16:22:29Z",
      "closed_at": "2018-05-18T16:22:29Z",
      "author_association": "NONE",
      "body": "Would it be possible to release an update on Pypi with latest geonames data?\r\n\r\nI tried to figure out how to update the JSON files but could not see where they come from on the geonames website.",
      "score": 1.0
    },
    {
      "url": "https://api.github.com/repos/yaph/d3-geomap/issues/45",
      "repository_url": "https://api.github.com/repos/yaph/d3-geomap",
      "labels_url": "https://api.github.com/repos/yaph/d3-geomap/issues/45/labels{/name}",
      "comments_url": "https://api.github.com/repos/yaph/d3-geomap/issues/45/comments",
      "events_url": "https://api.github.com/repos/yaph/d3-geomap/issues/45/events",
      "html_url": "https://github.com/yaph/d3-geomap/issues/45",
      "id": 300976571,
      "node_id": "MDU6SXNzdWUzMDA5NzY1NzE=",
      "number": 45,
      "title": "onClick event in d3-geomap",
      "user": {
        "login": "srh-ocean1991",
        "id": 3996056,
        "node_id": "MDQ6VXNlcjM5OTYwNTY=",
        "avatar_url": "https://avatars3.githubusercontent.com/u/3996056?v=4",
        "gravatar_id": "",
        "url": "https://api.github.com/users/srh-ocean1991",
        "html_url": "https://github.com/srh-ocean1991",
        "followers_url": "https://api.github.com/users/srh-ocean1991/followers",
        "following_url": "https://api.github.com/users/srh-ocean1991/following{/other_user}",
        "gists_url": "https://api.github.com/users/srh-ocean1991/gists{/gist_id}",
        "starred_url": "https://api.github.com/users/srh-ocean1991/starred{/owner}{/repo}",
        "subscriptions_url": "https://api.github.com/users/srh-ocean1991/subscriptions",
        "organizations_url": "https://api.github.com/users/srh-ocean1991/orgs",
        "repos_url": "https://api.github.com/users/srh-ocean1991/repos",
        "events_url": "https://api.github.com/users/srh-ocean1991/events{/privacy}",
        "received_events_url": "https://api.github.com/users/srh-ocean1991/received_events",
        "type": "User",
        "site_admin": false
      },
      "labels": [

      ],
      "state": "closed",
      "locked": false,
      "assignee": null,
      "assignees": [

      ],
      "milestone": null,
      "comments": 1,
      "created_at": "2018-02-28T10:48:06Z",
      "updated_at": "2018-04-27T10:47:28Z",
      "closed_at": "2018-04-27T10:47:28Z",
      "author_association": "NONE",
      "body": "\r\n0\r\ndown vote\r\nfavorite\r\nI'm trying to change onclick event in d3-geomap from zoom to another function. How can I do this ?\r\n\r\nThanks\r\n\r\nmy code is here :\r\n\r\n```\r\nvar map = d3.geomap.choropleth()\r\n            .geofile('json/IRN2.json')\r\n            .unitId('fips')\r\n            .projection(function(){return d3.geo.albers().center([51,35]);})\r\n            .column('point')\r\n            .scale(2000)\r\n            .rotate([-40, 0])\r\n            .translate([1.25*width ,-200 ])\r\n            .colors(['green','yellow' , 'pink' ,'red'])\r\n            .domain([0, 20 , 50,100])\r\n            //.clicked(function(){console.log(\"hiiiiiiiiiiiiiiii\");})\r\n            .legend(true);\r\n\r\n\r\n          d3.select('#map')\r\n            .datum(mydata)\r\n            .call(map.draw, map);\r\n```",
      "score": 1.0
    },
    {
      "url": "https://api.github.com/repos/yaph/twitter-tools/issues/1",
      "repository_url": "https://api.github.com/repos/yaph/twitter-tools",
      "labels_url": "https://api.github.com/repos/yaph/twitter-tools/issues/1/labels{/name}",
      "comments_url": "https://api.github.com/repos/yaph/twitter-tools/issues/1/comments",
      "events_url": "https://api.github.com/repos/yaph/twitter-tools/issues/1/events",
      "html_url": "https://github.com/yaph/twitter-tools/issues/1",
      "id": 46201072,
      "node_id": "MDU6SXNzdWU0NjIwMTA3Mg==",
      "number": 1,
      "title": "Unify collect scripts into one useful tool, with configurable data store.",
      "user": {
        "login": "yaph",
        "id": 60051,
        "node_id": "MDQ6VXNlcjYwMDUx",
        "avatar_url": "https://avatars3.githubusercontent.com/u/60051?v=4",
        "gravatar_id": "",
        "url": "https://api.github.com/users/yaph",
        "html_url": "https://github.com/yaph",
        "followers_url": "https://api.github.com/users/yaph/followers",
        "following_url": "https://api.github.com/users/yaph/following{/other_user}",
        "gists_url": "https://api.github.com/users/yaph/gists{/gist_id}",
        "starred_url": "https://api.github.com/users/yaph/starred{/owner}{/repo}",
        "subscriptions_url": "https://api.github.com/users/yaph/subscriptions",
        "organizations_url": "https://api.github.com/users/yaph/orgs",
        "repos_url": "https://api.github.com/users/yaph/repos",
        "events_url": "https://api.github.com/users/yaph/events{/privacy}",
        "received_events_url": "https://api.github.com/users/yaph/received_events",
        "type": "User",
        "site_admin": false
      },
      "labels": [

      ],
      "state": "closed",
      "locked": true,
      "assignee": null,
      "assignees": [

      ],
      "milestone": null,
      "comments": 1,
      "created_at": "2014-10-19T09:37:50Z",
      "updated_at": "2018-03-06T23:52:50Z",
      "closed_at": "2018-03-06T23:52:50Z",
      "author_association": "OWNER",
      "body": "",
      "score": 1.0
    },
    {
      "url": "https://api.github.com/repos/yaph/geonamescache/issues/12",
      "repository_url": "https://api.github.com/repos/yaph/geonamescache",
      "labels_url": "https://api.github.com/repos/yaph/geonamescache/issues/12/labels{/name}",
      "comments_url": "https://api.github.com/repos/yaph/geonamescache/issues/12/comments",
      "events_url": "https://api.github.com/repos/yaph/geonamescache/issues/12/events",
      "html_url": "https://github.com/yaph/geonamescache/issues/12",
      "id": 163339364,
      "node_id": "MDU6SXNzdWUxNjMzMzkzNjQ=",
      "number": 12,
      "title": "Python 3 support",
      "user": {
        "login": "dulrich15",
        "id": 1817139,
        "node_id": "MDQ6VXNlcjE4MTcxMzk=",
        "avatar_url": "https://avatars2.githubusercontent.com/u/1817139?v=4",
        "gravatar_id": "",
        "url": "https://api.github.com/users/dulrich15",
        "html_url": "https://github.com/dulrich15",
        "followers_url": "https://api.github.com/users/dulrich15/followers",
        "following_url": "https://api.github.com/users/dulrich15/following{/other_user}",
        "gists_url": "https://api.github.com/users/dulrich15/gists{/gist_id}",
        "starred_url": "https://api.github.com/users/dulrich15/starred{/owner}{/repo}",
        "subscriptions_url": "https://api.github.com/users/dulrich15/subscriptions",
        "organizations_url": "https://api.github.com/users/dulrich15/orgs",
        "repos_url": "https://api.github.com/users/dulrich15/repos",
        "events_url": "https://api.github.com/users/dulrich15/events{/privacy}",
        "received_events_url": "https://api.github.com/users/dulrich15/received_events",
        "type": "User",
        "site_admin": false
      },
      "labels": [

      ],
      "state": "closed",
      "locked": false,
      "assignee": null,
      "assignees": [

      ],
      "milestone": null,
      "comments": 4,
      "created_at": "2016-07-01T07:52:52Z",
      "updated_at": "2017-12-01T10:46:14Z",
      "closed_at": "2016-09-25T21:16:53Z",
      "author_association": "NONE",
      "body": "Getting a UnicodeDecodeError when trying to install with Python 3.5.\n\nThanks,\nDave\n",
      "score": 1.0
    },
    {
      "url": "https://api.github.com/repos/yaph/logya/issues/82",
      "repository_url": "https://api.github.com/repos/yaph/logya",
      "labels_url": "https://api.github.com/repos/yaph/logya/issues/82/labels{/name}",
      "comments_url": "https://api.github.com/repos/yaph/logya/issues/82/comments",
      "events_url": "https://api.github.com/repos/yaph/logya/issues/82/events",
      "html_url": "https://github.com/yaph/logya/issues/82",
      "id": 246138957,
      "node_id": "MDU6SXNzdWUyNDYxMzg5NTc=",
      "number": 82,
      "title": "Don't format titles of indexes and rss feeds",
      "user": {
        "login": "yaph",
        "id": 60051,
        "node_id": "MDQ6VXNlcjYwMDUx",
        "avatar_url": "https://avatars3.githubusercontent.com/u/60051?v=4",
        "gravatar_id": "",
        "url": "https://api.github.com/users/yaph",
        "html_url": "https://github.com/yaph",
        "followers_url": "https://api.github.com/users/yaph/followers",
        "following_url": "https://api.github.com/users/yaph/following{/other_user}",
        "gists_url": "https://api.github.com/users/yaph/gists{/gist_id}",
        "starred_url": "https://api.github.com/users/yaph/starred{/owner}{/repo}",
        "subscriptions_url": "https://api.github.com/users/yaph/subscriptions",
        "organizations_url": "https://api.github.com/users/yaph/orgs",
        "repos_url": "https://api.github.com/users/yaph/repos",
        "events_url": "https://api.github.com/users/yaph/events{/privacy}",
        "received_events_url": "https://api.github.com/users/yaph/received_events",
        "type": "User",
        "site_admin": false
      },
      "labels": [
        {
          "id": 57851987,
          "node_id": "MDU6TGFiZWw1Nzg1MTk4Nw==",
          "url": "https://api.github.com/repos/yaph/logya/labels/Backwards%20Incompatible",
          "name": "Backwards Incompatible",
          "color": "eb6420",
          "default": false
        }
      ],
      "state": "open",
      "locked": false,
      "assignee": null,
      "assignees": [

      ],
      "milestone": {
        "url": "https://api.github.com/repos/yaph/logya/milestones/5",
        "html_url": "https://github.com/yaph/logya/milestone/5",
        "labels_url": "https://api.github.com/repos/yaph/logya/milestones/5/labels",
        "id": 1107505,
        "node_id": "MDk6TWlsZXN0b25lMTEwNzUwNQ==",
        "number": 5,
        "title": "Better Document Index",
        "description": "",
        "creator": {
          "login": "yaph",
          "id": 60051,
          "node_id": "MDQ6VXNlcjYwMDUx",
          "avatar_url": "https://avatars3.githubusercontent.com/u/60051?v=4",
          "gravatar_id": "",
          "url": "https://api.github.com/users/yaph",
          "html_url": "https://github.com/yaph",
          "followers_url": "https://api.github.com/users/yaph/followers",
          "following_url": "https://api.github.com/users/yaph/following{/other_user}",
          "gists_url": "https://api.github.com/users/yaph/gists{/gist_id}",
          "starred_url": "https://api.github.com/users/yaph/starred{/owner}{/repo}",
          "subscriptions_url": "https://api.github.com/users/yaph/subscriptions",
          "organizations_url": "https://api.github.com/users/yaph/orgs",
          "repos_url": "https://api.github.com/users/yaph/repos",
          "events_url": "https://api.github.com/users/yaph/events{/privacy}",
          "received_events_url": "https://api.github.com/users/yaph/received_events",
          "type": "User",
          "site_admin": false
        },
        "open_issues": 5,
        "closed_issues": 5,
        "state": "open",
        "created_at": "2015-05-12T20:31:55Z",
        "updated_at": "2019-01-24T00:40:46Z",
        "due_on": null,
        "closed_at": null
      },
      "comments": 0,
      "created_at": "2017-07-27T19:05:37Z",
      "updated_at": "2017-07-27T19:05:37Z",
      "closed_at": null,
      "author_association": "OWNER",
      "body": "Leave it to the template to do the formatting.",
      "score": 1.0
    },
    {
      "url": "https://api.github.com/repos/yaph/d3-geomap/issues/41",
      "repository_url": "https://api.github.com/repos/yaph/d3-geomap",
      "labels_url": "https://api.github.com/repos/yaph/d3-geomap/issues/41/labels{/name}",
      "comments_url": "https://api.github.com/repos/yaph/d3-geomap/issues/41/comments",
      "events_url": "https://api.github.com/repos/yaph/d3-geomap/issues/41/events",
      "html_url": "https://github.com/yaph/d3-geomap/issues/41",
      "id": 232053089,
      "node_id": "MDU6SXNzdWUyMzIwNTMwODk=",
      "number": 41,
      "title": "d3.geomap 2.0.0alpha: \"this is null\" in choropleth.draw in FireFox and iOS",
      "user": {
        "login": "yaph",
        "id": 60051,
        "node_id": "MDQ6VXNlcjYwMDUx",
        "avatar_url": "https://avatars3.githubusercontent.com/u/60051?v=4",
        "gravatar_id": "",
        "url": "https://api.github.com/users/yaph",
        "html_url": "https://github.com/yaph",
        "followers_url": "https://api.github.com/users/yaph/followers",
        "following_url": "https://api.github.com/users/yaph/following{/other_user}",
        "gists_url": "https://api.github.com/users/yaph/gists{/gist_id}",
        "starred_url": "https://api.github.com/users/yaph/starred{/owner}{/repo}",
        "subscriptions_url": "https://api.github.com/users/yaph/subscriptions",
        "organizations_url": "https://api.github.com/users/yaph/orgs",
        "repos_url": "https://api.github.com/users/yaph/repos",
        "events_url": "https://api.github.com/users/yaph/events{/privacy}",
        "received_events_url": "https://api.github.com/users/yaph/received_events",
        "type": "User",
        "site_admin": false
      },
      "labels": [

      ],
      "state": "closed",
      "locked": false,
      "assignee": null,
      "assignees": [

      ],
      "milestone": {
        "url": "https://api.github.com/repos/yaph/d3-geomap/milestones/1",
        "html_url": "https://github.com/yaph/d3-geomap/milestone/1",
        "labels_url": "https://api.github.com/repos/yaph/d3-geomap/milestones/1/labels",
        "id": 2548765,
        "node_id": "MDk6TWlsZXN0b25lMjU0ODc2NQ==",
        "number": 1,
        "title": "v2",
        "description": null,
        "creator": {
          "login": "yaph",
          "id": 60051,
          "node_id": "MDQ6VXNlcjYwMDUx",
          "avatar_url": "https://avatars3.githubusercontent.com/u/60051?v=4",
          "gravatar_id": "",
          "url": "https://api.github.com/users/yaph",
          "html_url": "https://github.com/yaph",
          "followers_url": "https://api.github.com/users/yaph/followers",
          "following_url": "https://api.github.com/users/yaph/following{/other_user}",
          "gists_url": "https://api.github.com/users/yaph/gists{/gist_id}",
          "starred_url": "https://api.github.com/users/yaph/starred{/owner}{/repo}",
          "subscriptions_url": "https://api.github.com/users/yaph/subscriptions",
          "organizations_url": "https://api.github.com/users/yaph/orgs",
          "repos_url": "https://api.github.com/users/yaph/repos",
          "events_url": "https://api.github.com/users/yaph/events{/privacy}",
          "received_events_url": "https://api.github.com/users/yaph/received_events",
          "type": "User",
          "site_admin": false
        },
        "open_issues": 0,
        "closed_issues": 3,
        "state": "open",
        "created_at": "2017-05-29T15:46:35Z",
        "updated_at": "2018-10-19T22:42:10Z",
        "due_on": null,
        "closed_at": null
      },
      "comments": 2,
      "created_at": "2017-05-29T15:37:25Z",
      "updated_at": "2017-05-30T20:11:43Z",
      "closed_at": "2017-05-30T20:11:43Z",
      "author_association": "OWNER",
      "body": "The super call fails since this is not defined and nothing gets drawn.",
      "score": 1.0
    },
    {
      "url": "https://api.github.com/repos/yaph/geonamescache/issues/13",
      "repository_url": "https://api.github.com/repos/yaph/geonamescache",
      "labels_url": "https://api.github.com/repos/yaph/geonamescache/issues/13/labels{/name}",
      "comments_url": "https://api.github.com/repos/yaph/geonamescache/issues/13/comments",
      "events_url": "https://api.github.com/repos/yaph/geonamescache/issues/13/events",
      "html_url": "https://github.com/yaph/geonamescache/pull/13",
      "id": 224618895,
      "node_id": "MDExOlB1bGxSZXF1ZXN0MTE3ODI0NDYz",
      "number": 13,
      "title": "GOV-522 Initial Draft",
      "user": {
        "login": "parthshah86",
        "id": 9012625,
        "node_id": "MDQ6VXNlcjkwMTI2MjU=",
        "avatar_url": "https://avatars1.githubusercontent.com/u/9012625?v=4",
        "gravatar_id": "",
        "url": "https://api.github.com/users/parthshah86",
        "html_url": "https://github.com/parthshah86",
        "followers_url": "https://api.github.com/users/parthshah86/followers",
        "following_url": "https://api.github.com/users/parthshah86/following{/other_user}",
        "gists_url": "https://api.github.com/users/parthshah86/gists{/gist_id}",
        "starred_url": "https://api.github.com/users/parthshah86/starred{/owner}{/repo}",
        "subscriptions_url": "https://api.github.com/users/parthshah86/subscriptions",
        "organizations_url": "https://api.github.com/users/parthshah86/orgs",
        "repos_url": "https://api.github.com/users/parthshah86/repos",
        "events_url": "https://api.github.com/users/parthshah86/events{/privacy}",
        "received_events_url": "https://api.github.com/users/parthshah86/received_events",
        "type": "User",
        "site_admin": false
      },
      "labels": [

      ],
      "state": "closed",
      "locked": false,
      "assignee": null,
      "assignees": [

      ],
      "milestone": null,
      "comments": 0,
      "created_at": "2017-04-26T22:33:41Z",
      "updated_at": "2017-05-17T22:02:28Z",
      "closed_at": "2017-04-26T22:34:10Z",
      "author_association": "NONE",
      "pull_request": {
        "url": "https://api.github.com/repos/yaph/geonamescache/pulls/13",
        "html_url": "https://github.com/yaph/geonamescache/pull/13",
        "diff_url": "https://github.com/yaph/geonamescache/pull/13.diff",
        "patch_url": "https://github.com/yaph/geonamescache/pull/13.patch"
      },
      "body": "",
      "score": 1.0
    },
    {
      "url": "https://api.github.com/repos/yaph/LEOlookup/issues/2",
      "repository_url": "https://api.github.com/repos/yaph/LEOlookup",
      "labels_url": "https://api.github.com/repos/yaph/LEOlookup/issues/2/labels{/name}",
      "comments_url": "https://api.github.com/repos/yaph/LEOlookup/issues/2/comments",
      "events_url": "https://api.github.com/repos/yaph/LEOlookup/issues/2/events",
      "html_url": "https://github.com/yaph/LEOlookup/issues/2",
      "id": 228483533,
      "node_id": "MDU6SXNzdWUyMjg0ODM1MzM=",
      "number": 2,
      "title": "Icon grayed out and extension not longer working",
      "user": {
        "login": "taiko000",
        "id": 1303932,
        "node_id": "MDQ6VXNlcjEzMDM5MzI=",
        "avatar_url": "https://avatars2.githubusercontent.com/u/1303932?v=4",
        "gravatar_id": "",
        "url": "https://api.github.com/users/taiko000",
        "html_url": "https://github.com/taiko000",
        "followers_url": "https://api.github.com/users/taiko000/followers",
        "following_url": "https://api.github.com/users/taiko000/following{/other_user}",
        "gists_url": "https://api.github.com/users/taiko000/gists{/gist_id}",
        "starred_url": "https://api.github.com/users/taiko000/starred{/owner}{/repo}",
        "subscriptions_url": "https://api.github.com/users/taiko000/subscriptions",
        "organizations_url": "https://api.github.com/users/taiko000/orgs",
        "repos_url": "https://api.github.com/users/taiko000/repos",
        "events_url": "https://api.github.com/users/taiko000/events{/privacy}",
        "received_events_url": "https://api.github.com/users/taiko000/received_events",
        "type": "User",
        "site_admin": false
      },
      "labels": [

      ],
      "state": "closed",
      "locked": false,
      "assignee": null,
      "assignees": [

      ],
      "milestone": null,
      "comments": 2,
      "created_at": "2017-05-13T16:21:11Z",
      "updated_at": "2017-05-13T19:11:08Z",
      "closed_at": "2017-05-13T19:11:08Z",
      "author_association": "NONE",
      "body": "The extension's icon next to the browser's address bar is grayed out and the extension does not longer work with the latest version of Google Chrome  58.0.3029.81 (64-bit). \r\nReinstalling the extension does not help. ",
      "score": 1.0
    },
    {
      "url": "https://api.github.com/repos/yaph/geonamescache/issues/17",
      "repository_url": "https://api.github.com/repos/yaph/geonamescache",
      "labels_url": "https://api.github.com/repos/yaph/geonamescache/issues/17/labels{/name}",
      "comments_url": "https://api.github.com/repos/yaph/geonamescache/issues/17/comments",
      "events_url": "https://api.github.com/repos/yaph/geonamescache/issues/17/events",
      "html_url": "https://github.com/yaph/geonamescache/pull/17",
      "id": 226382905,
      "node_id": "MDExOlB1bGxSZXF1ZXN0MTE5MDQ3NjM3",
      "number": 17,
      "title": "Cleanup and more alternative names",
      "user": {
        "login": "mwu1993",
        "id": 1650674,
        "node_id": "MDQ6VXNlcjE2NTA2NzQ=",
        "avatar_url": "https://avatars1.githubusercontent.com/u/1650674?v=4",
        "gravatar_id": "",
        "url": "https://api.github.com/users/mwu1993",
        "html_url": "https://github.com/mwu1993",
        "followers_url": "https://api.github.com/users/mwu1993/followers",
        "following_url": "https://api.github.com/users/mwu1993/following{/other_user}",
        "gists_url": "https://api.github.com/users/mwu1993/gists{/gist_id}",
        "starred_url": "https://api.github.com/users/mwu1993/starred{/owner}{/repo}",
        "subscriptions_url": "https://api.github.com/users/mwu1993/subscriptions",
        "organizations_url": "https://api.github.com/users/mwu1993/orgs",
        "repos_url": "https://api.github.com/users/mwu1993/repos",
        "events_url": "https://api.github.com/users/mwu1993/events{/privacy}",
        "received_events_url": "https://api.github.com/users/mwu1993/received_events",
        "type": "User",
        "site_admin": false
      },
      "labels": [

      ],
      "state": "closed",
      "locked": false,
      "assignee": null,
      "assignees": [

      ],
      "milestone": null,
      "comments": 0,
      "created_at": "2017-05-04T19:22:59Z",
      "updated_at": "2017-05-04T19:24:06Z",
      "closed_at": "2017-05-04T19:23:03Z",
      "author_association": "NONE",
      "pull_request": {
        "url": "https://api.github.com/repos/yaph/geonamescache/pulls/17",
        "html_url": "https://github.com/yaph/geonamescache/pull/17",
        "diff_url": "https://github.com/yaph/geonamescache/pull/17.diff",
        "patch_url": "https://github.com/yaph/geonamescache/pull/17.patch"
      },
      "body": "Some cleanup logic for OSM names and adding updated alternative names for both geonames and osm names.",
      "score": 1.0
    },
    {
      "url": "https://api.github.com/repos/yaph/geonamescache/issues/15",
      "repository_url": "https://api.github.com/repos/yaph/geonamescache",
      "labels_url": "https://api.github.com/repos/yaph/geonamescache/issues/15/labels{/name}",
      "comments_url": "https://api.github.com/repos/yaph/geonamescache/issues/15/comments",
      "events_url": "https://api.github.com/repos/yaph/geonamescache/issues/15/events",
      "html_url": "https://github.com/yaph/geonamescache/pull/15",
      "id": 224868244,
      "node_id": "MDExOlB1bGxSZXF1ZXN0MTE3OTk5MzQw",
      "number": 15,
      "title": "Michael/osm data",
      "user": {
        "login": "mwu1993",
        "id": 1650674,
        "node_id": "MDQ6VXNlcjE2NTA2NzQ=",
        "avatar_url": "https://avatars1.githubusercontent.com/u/1650674?v=4",
        "gravatar_id": "",
        "url": "https://api.github.com/users/mwu1993",
        "html_url": "https://github.com/mwu1993",
        "followers_url": "https://api.github.com/users/mwu1993/followers",
        "following_url": "https://api.github.com/users/mwu1993/following{/other_user}",
        "gists_url": "https://api.github.com/users/mwu1993/gists{/gist_id}",
        "starred_url": "https://api.github.com/users/mwu1993/starred{/owner}{/repo}",
        "subscriptions_url": "https://api.github.com/users/mwu1993/subscriptions",
        "organizations_url": "https://api.github.com/users/mwu1993/orgs",
        "repos_url": "https://api.github.com/users/mwu1993/repos",
        "events_url": "https://api.github.com/users/mwu1993/events{/privacy}",
        "received_events_url": "https://api.github.com/users/mwu1993/received_events",
        "type": "User",
        "site_admin": false
      },
      "labels": [

      ],
      "state": "closed",
      "locked": false,
      "assignee": null,
      "assignees": [

      ],
      "milestone": null,
      "comments": 0,
      "created_at": "2017-04-27T18:11:30Z",
      "updated_at": "2017-05-02T20:27:13Z",
      "closed_at": "2017-04-27T18:11:50Z",
      "author_association": "NONE",
      "pull_request": {
        "url": "https://api.github.com/repos/yaph/geonamescache/pulls/15",
        "html_url": "https://github.com/yaph/geonamescache/pull/15",
        "diff_url": "https://github.com/yaph/geonamescache/pull/15.diff",
        "patch_url": "https://github.com/yaph/geonamescache/pull/15.patch"
      },
      "body": "Added OSM data source with search module, and script to crawl wikipedia for alternate names.",
      "score": 1.0
    },
    {
      "url": "https://api.github.com/repos/yaph/geonamescache/issues/14",
      "repository_url": "https://api.github.com/repos/yaph/geonamescache",
      "labels_url": "https://api.github.com/repos/yaph/geonamescache/issues/14/labels{/name}",
      "comments_url": "https://api.github.com/repos/yaph/geonamescache/issues/14/comments",
      "events_url": "https://api.github.com/repos/yaph/geonamescache/issues/14/events",
      "html_url": "https://github.com/yaph/geonamescache/pull/14",
      "id": 224867359,
      "node_id": "MDExOlB1bGxSZXF1ZXN0MTE3OTk4Njcx",
      "number": 14,
      "title": "Michael/osm data",
      "user": {
        "login": "mwu1993",
        "id": 1650674,
        "node_id": "MDQ6VXNlcjE2NTA2NzQ=",
        "avatar_url": "https://avatars1.githubusercontent.com/u/1650674?v=4",
        "gravatar_id": "",
        "url": "https://api.github.com/users/mwu1993",
        "html_url": "https://github.com/mwu1993",
        "followers_url": "https://api.github.com/users/mwu1993/followers",
        "following_url": "https://api.github.com/users/mwu1993/following{/other_user}",
        "gists_url": "https://api.github.com/users/mwu1993/gists{/gist_id}",
        "starred_url": "https://api.github.com/users/mwu1993/starred{/owner}{/repo}",
        "subscriptions_url": "https://api.github.com/users/mwu1993/subscriptions",
        "organizations_url": "https://api.github.com/users/mwu1993/orgs",
        "repos_url": "https://api.github.com/users/mwu1993/repos",
        "events_url": "https://api.github.com/users/mwu1993/events{/privacy}",
        "received_events_url": "https://api.github.com/users/mwu1993/received_events",
        "type": "User",
        "site_admin": false
      },
      "labels": [

      ],
      "state": "closed",
      "locked": false,
      "assignee": null,
      "assignees": [

      ],
      "milestone": null,
      "comments": 0,
      "created_at": "2017-04-27T18:08:09Z",
      "updated_at": "2017-05-02T20:27:13Z",
      "closed_at": "2017-04-27T18:09:11Z",
      "author_association": "NONE",
      "pull_request": {
        "url": "https://api.github.com/repos/yaph/geonamescache/pulls/14",
        "html_url": "https://github.com/yaph/geonamescache/pull/14",
        "diff_url": "https://github.com/yaph/geonamescache/pull/14.diff",
        "patch_url": "https://github.com/yaph/geonamescache/pull/14.patch"
      },
      "body": "Added OSM data source with search module,  and script for crawling wiki for alternate names.",
      "score": 1.0
    },
    {
      "url": "https://api.github.com/repos/yaph/geonamescache/issues/16",
      "repository_url": "https://api.github.com/repos/yaph/geonamescache",
      "labels_url": "https://api.github.com/repos/yaph/geonamescache/issues/16/labels{/name}",
      "comments_url": "https://api.github.com/repos/yaph/geonamescache/issues/16/comments",
      "events_url": "https://api.github.com/repos/yaph/geonamescache/issues/16/events",
      "html_url": "https://github.com/yaph/geonamescache/pull/16",
      "id": 225810682,
      "node_id": "MDExOlB1bGxSZXF1ZXN0MTE4NjM4NjY2",
      "number": 16,
      "title": "Michael/cleanup",
      "user": {
        "login": "mwu1993",
        "id": 1650674,
        "node_id": "MDQ6VXNlcjE2NTA2NzQ=",
        "avatar_url": "https://avatars1.githubusercontent.com/u/1650674?v=4",
        "gravatar_id": "",
        "url": "https://api.github.com/users/mwu1993",
        "html_url": "https://github.com/mwu1993",
        "followers_url": "https://api.github.com/users/mwu1993/followers",
        "following_url": "https://api.github.com/users/mwu1993/following{/other_user}",
        "gists_url": "https://api.github.com/users/mwu1993/gists{/gist_id}",
        "starred_url": "https://api.github.com/users/mwu1993/starred{/owner}{/repo}",
        "subscriptions_url": "https://api.github.com/users/mwu1993/subscriptions",
        "organizations_url": "https://api.github.com/users/mwu1993/orgs",
        "repos_url": "https://api.github.com/users/mwu1993/repos",
        "events_url": "https://api.github.com/users/mwu1993/events{/privacy}",
        "received_events_url": "https://api.github.com/users/mwu1993/received_events",
        "type": "User",
        "site_admin": false
      },
      "labels": [

      ],
      "state": "closed",
      "locked": false,
      "assignee": null,
      "assignees": [

      ],
      "milestone": null,
      "comments": 0,
      "created_at": "2017-05-02T20:25:00Z",
      "updated_at": "2017-05-02T20:26:57Z",
      "closed_at": "2017-05-02T20:25:03Z",
      "author_association": "NONE",
      "pull_request": {
        "url": "https://api.github.com/repos/yaph/geonamescache/pulls/16",
        "html_url": "https://github.com/yaph/geonamescache/pull/16",
        "diff_url": "https://github.com/yaph/geonamescache/pull/16.diff",
        "patch_url": "https://github.com/yaph/geonamescache/pull/16.patch"
      },
      "body": "Modified some data field names and values, move everything into geonamescache directory, returned copied dictionaries from locations search.",
      "score": 1.0
    },
    {
      "url": "https://api.github.com/repos/yaph/webshots/issues/4",
      "repository_url": "https://api.github.com/repos/yaph/webshots",
      "labels_url": "https://api.github.com/repos/yaph/webshots/issues/4/labels{/name}",
      "comments_url": "https://api.github.com/repos/yaph/webshots/issues/4/comments",
      "events_url": "https://api.github.com/repos/yaph/webshots/issues/4/events",
      "html_url": "https://github.com/yaph/webshots/pull/4",
      "id": 223864558,
      "node_id": "MDExOlB1bGxSZXF1ZXN0MTE3Mjk2ODg5",
      "number": 4,
      "title": "Added Install, Uninstall Scripts",
      "user": {
        "login": "a904guy",
        "id": 404081,
        "node_id": "MDQ6VXNlcjQwNDA4MQ==",
        "avatar_url": "https://avatars2.githubusercontent.com/u/404081?v=4",
        "gravatar_id": "",
        "url": "https://api.github.com/users/a904guy",
        "html_url": "https://github.com/a904guy",
        "followers_url": "https://api.github.com/users/a904guy/followers",
        "following_url": "https://api.github.com/users/a904guy/following{/other_user}",
        "gists_url": "https://api.github.com/users/a904guy/gists{/gist_id}",
        "starred_url": "https://api.github.com/users/a904guy/starred{/owner}{/repo}",
        "subscriptions_url": "https://api.github.com/users/a904guy/subscriptions",
        "organizations_url": "https://api.github.com/users/a904guy/orgs",
        "repos_url": "https://api.github.com/users/a904guy/repos",
        "events_url": "https://api.github.com/users/a904guy/events{/privacy}",
        "received_events_url": "https://api.github.com/users/a904guy/received_events",
        "type": "User",
        "site_admin": false
      },
      "labels": [

      ],
      "state": "closed",
      "locked": false,
      "assignee": null,
      "assignees": [

      ],
      "milestone": null,
      "comments": 2,
      "created_at": "2017-04-24T15:46:02Z",
      "updated_at": "2017-04-28T20:24:46Z",
      "closed_at": "2017-04-24T20:20:39Z",
      "author_association": "NONE",
      "pull_request": {
        "url": "https://api.github.com/repos/yaph/webshots/pulls/4",
        "html_url": "https://github.com/yaph/webshots/pull/4",
        "diff_url": "https://github.com/yaph/webshots/pull/4.diff",
        "patch_url": "https://github.com/yaph/webshots/pull/4.patch"
      },
      "body": "./install.sh\r\n./uninstall.sh\r\n\r\nWill work on linux-ish systems, including Mac OSX.",
      "score": 1.0
    },
    {
      "url": "https://api.github.com/repos/yaph/d3-geomap/issues/40",
      "repository_url": "https://api.github.com/repos/yaph/d3-geomap",
      "labels_url": "https://api.github.com/repos/yaph/d3-geomap/issues/40/labels{/name}",
      "comments_url": "https://api.github.com/repos/yaph/d3-geomap/issues/40/comments",
      "events_url": "https://api.github.com/repos/yaph/d3-geomap/issues/40/events",
      "html_url": "https://github.com/yaph/d3-geomap/issues/40",
      "id": 202352071,
      "node_id": "MDU6SXNzdWUyMDIzNTIwNzE=",
      "number": 40,
      "title": "geomap.min.js broken",
      "user": {
        "login": "capndave",
        "id": 15132517,
        "node_id": "MDQ6VXNlcjE1MTMyNTE3",
        "avatar_url": "https://avatars1.githubusercontent.com/u/15132517?v=4",
        "gravatar_id": "",
        "url": "https://api.github.com/users/capndave",
        "html_url": "https://github.com/capndave",
        "followers_url": "https://api.github.com/users/capndave/followers",
        "following_url": "https://api.github.com/users/capndave/following{/other_user}",
        "gists_url": "https://api.github.com/users/capndave/gists{/gist_id}",
        "starred_url": "https://api.github.com/users/capndave/starred{/owner}{/repo}",
        "subscriptions_url": "https://api.github.com/users/capndave/subscriptions",
        "organizations_url": "https://api.github.com/users/capndave/orgs",
        "repos_url": "https://api.github.com/users/capndave/repos",
        "events_url": "https://api.github.com/users/capndave/events{/privacy}",
        "received_events_url": "https://api.github.com/users/capndave/received_events",
        "type": "User",
        "site_admin": false
      },
      "labels": [

      ],
      "state": "closed",
      "locked": false,
      "assignee": null,
      "assignees": [

      ],
      "milestone": null,
      "comments": 3,
      "created_at": "2017-01-22T01:24:13Z",
      "updated_at": "2017-01-25T22:16:43Z",
      "closed_at": "2017-01-25T22:16:43Z",
      "author_association": "NONE",
      "body": "When using the basic code on your intro page (at http://d3-geomap.github.io/), I get the following error:\r\nTypeError: d is undefined (at 1:20972). Still not able to get a basic map running. ",
      "score": 1.0
    },
    {
      "url": "https://api.github.com/repos/yaph/programming-languages-influence/issues/2",
      "repository_url": "https://api.github.com/repos/yaph/programming-languages-influence",
      "labels_url": "https://api.github.com/repos/yaph/programming-languages-influence/issues/2/labels{/name}",
      "comments_url": "https://api.github.com/repos/yaph/programming-languages-influence/issues/2/comments",
      "events_url": "https://api.github.com/repos/yaph/programming-languages-influence/issues/2/events",
      "html_url": "https://github.com/yaph/programming-languages-influence/issues/2",
      "id": 197518742,
      "node_id": "MDU6SXNzdWUxOTc1MTg3NDI=",
      "number": 2,
      "title": "Rust isn't included",
      "user": {
        "login": "CorruptComputer",
        "id": 5573038,
        "node_id": "MDQ6VXNlcjU1NzMwMzg=",
        "avatar_url": "https://avatars0.githubusercontent.com/u/5573038?v=4",
        "gravatar_id": "",
        "url": "https://api.github.com/users/CorruptComputer",
        "html_url": "https://github.com/CorruptComputer",
        "followers_url": "https://api.github.com/users/CorruptComputer/followers",
        "following_url": "https://api.github.com/users/CorruptComputer/following{/other_user}",
        "gists_url": "https://api.github.com/users/CorruptComputer/gists{/gist_id}",
        "starred_url": "https://api.github.com/users/CorruptComputer/starred{/owner}{/repo}",
        "subscriptions_url": "https://api.github.com/users/CorruptComputer/subscriptions",
        "organizations_url": "https://api.github.com/users/CorruptComputer/orgs",
        "repos_url": "https://api.github.com/users/CorruptComputer/repos",
        "events_url": "https://api.github.com/users/CorruptComputer/events{/privacy}",
        "received_events_url": "https://api.github.com/users/CorruptComputer/received_events",
        "type": "User",
        "site_admin": false
      },
      "labels": [

      ],
      "state": "closed",
      "locked": false,
      "assignee": null,
      "assignees": [

      ],
      "milestone": null,
      "comments": 5,
      "created_at": "2016-12-25T23:23:44Z",
      "updated_at": "2017-01-08T15:18:37Z",
      "closed_at": "2017-01-08T15:18:37Z",
      "author_association": "NONE",
      "body": "Also it seems that freebase has been deprecated.",
      "score": 1.0
    },
    {
      "url": "https://api.github.com/repos/yaph/logya/issues/29",
      "repository_url": "https://api.github.com/repos/yaph/logya",
      "labels_url": "https://api.github.com/repos/yaph/logya/issues/29/labels{/name}",
      "comments_url": "https://api.github.com/repos/yaph/logya/issues/29/comments",
      "events_url": "https://api.github.com/repos/yaph/logya/issues/29/events",
      "html_url": "https://github.com/yaph/logya/issues/29",
      "id": 27376755,
      "node_id": "MDU6SXNzdWUyNzM3Njc1NQ==",
      "number": 29,
      "title": "Handle Exceptions",
      "user": {
        "login": "yaph",
        "id": 60051,
        "node_id": "MDQ6VXNlcjYwMDUx",
        "avatar_url": "https://avatars3.githubusercontent.com/u/60051?v=4",
        "gravatar_id": "",
        "url": "https://api.github.com/users/yaph",
        "html_url": "https://github.com/yaph",
        "followers_url": "https://api.github.com/users/yaph/followers",
        "following_url": "https://api.github.com/users/yaph/following{/other_user}",
        "gists_url": "https://api.github.com/users/yaph/gists{/gist_id}",
        "starred_url": "https://api.github.com/users/yaph/starred{/owner}{/repo}",
        "subscriptions_url": "https://api.github.com/users/yaph/subscriptions",
        "organizations_url": "https://api.github.com/users/yaph/orgs",
        "repos_url": "https://api.github.com/users/yaph/repos",
        "events_url": "https://api.github.com/users/yaph/events{/privacy}",
        "received_events_url": "https://api.github.com/users/yaph/received_events",
        "type": "User",
        "site_admin": false
      },
      "labels": [
        {
          "id": 55509211,
          "node_id": "MDU6TGFiZWw1NTUwOTIxMQ==",
          "url": "https://api.github.com/repos/yaph/logya/labels/Enhancement",
          "name": "Enhancement",
          "color": "009800",
          "default": false
        }
      ],
      "state": "closed",
      "locked": false,
      "assignee": {
        "login": "yaph",
        "id": 60051,
        "node_id": "MDQ6VXNlcjYwMDUx",
        "avatar_url": "https://avatars3.githubusercontent.com/u/60051?v=4",
        "gravatar_id": "",
        "url": "https://api.github.com/users/yaph",
        "html_url": "https://github.com/yaph",
        "followers_url": "https://api.github.com/users/yaph/followers",
        "following_url": "https://api.github.com/users/yaph/following{/other_user}",
        "gists_url": "https://api.github.com/users/yaph/gists{/gist_id}",
        "starred_url": "https://api.github.com/users/yaph/starred{/owner}{/repo}",
        "subscriptions_url": "https://api.github.com/users/yaph/subscriptions",
        "organizations_url": "https://api.github.com/users/yaph/orgs",
        "repos_url": "https://api.github.com/users/yaph/repos",
        "events_url": "https://api.github.com/users/yaph/events{/privacy}",
        "received_events_url": "https://api.github.com/users/yaph/received_events",
        "type": "User",
        "site_admin": false
      },
      "assignees": [
        {
          "login": "yaph",
          "id": 60051,
          "node_id": "MDQ6VXNlcjYwMDUx",
          "avatar_url": "https://avatars3.githubusercontent.com/u/60051?v=4",
          "gravatar_id": "",
          "url": "https://api.github.com/users/yaph",
          "html_url": "https://github.com/yaph",
          "followers_url": "https://api.github.com/users/yaph/followers",
          "following_url": "https://api.github.com/users/yaph/following{/other_user}",
          "gists_url": "https://api.github.com/users/yaph/gists{/gist_id}",
          "starred_url": "https://api.github.com/users/yaph/starred{/owner}{/repo}",
          "subscriptions_url": "https://api.github.com/users/yaph/subscriptions",
          "organizations_url": "https://api.github.com/users/yaph/orgs",
          "repos_url": "https://api.github.com/users/yaph/repos",
          "events_url": "https://api.github.com/users/yaph/events{/privacy}",
          "received_events_url": "https://api.github.com/users/yaph/received_events",
          "type": "User",
          "site_admin": false
        }
      ],
      "milestone": {
        "url": "https://api.github.com/repos/yaph/logya/milestones/4",
        "html_url": "https://github.com/yaph/logya/milestone/4",
        "labels_url": "https://api.github.com/repos/yaph/logya/milestones/4/labels",
        "id": 1098339,
        "node_id": "MDk6TWlsZXN0b25lMTA5ODMzOQ==",
        "number": 4,
        "title": "4.0",
        "description": "",
        "creator": {
          "login": "yaph",
          "id": 60051,
          "node_id": "MDQ6VXNlcjYwMDUx",
          "avatar_url": "https://avatars3.githubusercontent.com/u/60051?v=4",
          "gravatar_id": "",
          "url": "https://api.github.com/users/yaph",
          "html_url": "https://github.com/yaph",
          "followers_url": "https://api.github.com/users/yaph/followers",
          "following_url": "https://api.github.com/users/yaph/following{/other_user}",
          "gists_url": "https://api.github.com/users/yaph/gists{/gist_id}",
          "starred_url": "https://api.github.com/users/yaph/starred{/owner}{/repo}",
          "subscriptions_url": "https://api.github.com/users/yaph/subscriptions",
          "organizations_url": "https://api.github.com/users/yaph/orgs",
          "repos_url": "https://api.github.com/users/yaph/repos",
          "events_url": "https://api.github.com/users/yaph/events{/privacy}",
          "received_events_url": "https://api.github.com/users/yaph/received_events",
          "type": "User",
          "site_admin": false
        },
        "open_issues": 0,
        "closed_issues": 12,
        "state": "open",
        "created_at": "2015-05-06T10:12:34Z",
        "updated_at": "2016-08-06T19:39:14Z",
        "due_on": null,
        "closed_at": null
      },
      "comments": 2,
      "created_at": "2014-02-11T19:11:07Z",
      "updated_at": "2016-12-19T21:51:46Z",
      "closed_at": "2016-01-03T18:55:17Z",
      "author_association": "OWNER",
      "body": "Currently invoking logya commands may cause exceptions that break the program and print a stacktrace which is not very user friendly. Think about a sane way to handle different kinds of exceptions, e. g. ParserException, LoaderException, WriterException...\n",
      "score": 1.0
    },
    {
      "url": "https://api.github.com/repos/yaph/d3-geomap/issues/39",
      "repository_url": "https://api.github.com/repos/yaph/d3-geomap",
      "labels_url": "https://api.github.com/repos/yaph/d3-geomap/issues/39/labels{/name}",
      "comments_url": "https://api.github.com/repos/yaph/d3-geomap/issues/39/comments",
      "events_url": "https://api.github.com/repos/yaph/d3-geomap/issues/39/events",
      "html_url": "https://github.com/yaph/d3-geomap/issues/39",
      "id": 194110889,
      "node_id": "MDU6SXNzdWUxOTQxMTA4ODk=",
      "number": 39,
      "title": "readme instructions error: cd d3.geomap, folder is d3-geomap",
      "user": {
        "login": "KalindiFonda",
        "id": 9532690,
        "node_id": "MDQ6VXNlcjk1MzI2OTA=",
        "avatar_url": "https://avatars0.githubusercontent.com/u/9532690?v=4",
        "gravatar_id": "",
        "url": "https://api.github.com/users/KalindiFonda",
        "html_url": "https://github.com/KalindiFonda",
        "followers_url": "https://api.github.com/users/KalindiFonda/followers",
        "following_url": "https://api.github.com/users/KalindiFonda/following{/other_user}",
        "gists_url": "https://api.github.com/users/KalindiFonda/gists{/gist_id}",
        "starred_url": "https://api.github.com/users/KalindiFonda/starred{/owner}{/repo}",
        "subscriptions_url": "https://api.github.com/users/KalindiFonda/subscriptions",
        "organizations_url": "https://api.github.com/users/KalindiFonda/orgs",
        "repos_url": "https://api.github.com/users/KalindiFonda/repos",
        "events_url": "https://api.github.com/users/KalindiFonda/events{/privacy}",
        "received_events_url": "https://api.github.com/users/KalindiFonda/received_events",
        "type": "User",
        "site_admin": false
      },
      "labels": [

      ],
      "state": "closed",
      "locked": false,
      "assignee": null,
      "assignees": [

      ],
      "milestone": null,
      "comments": 1,
      "created_at": "2016-12-07T17:17:40Z",
      "updated_at": "2016-12-12T00:27:38Z",
      "closed_at": "2016-12-12T00:27:38Z",
      "author_association": "NONE",
      "body": "",
      "score": 1.0
    },
    {
      "url": "https://api.github.com/repos/yaph/logya/issues/81",
      "repository_url": "https://api.github.com/repos/yaph/logya",
      "labels_url": "https://api.github.com/repos/yaph/logya/issues/81/labels{/name}",
      "comments_url": "https://api.github.com/repos/yaph/logya/issues/81/comments",
      "events_url": "https://api.github.com/repos/yaph/logya/issues/81/events",
      "html_url": "https://github.com/yaph/logya/issues/81",
      "id": 187601265,
      "node_id": "MDU6SXNzdWUxODc2MDEyNjU=",
      "number": 81,
      "title": "Check performance impact of using the multiprocessing module",
      "user": {
        "login": "yaph",
        "id": 60051,
        "node_id": "MDQ6VXNlcjYwMDUx",
        "avatar_url": "https://avatars3.githubusercontent.com/u/60051?v=4",
        "gravatar_id": "",
        "url": "https://api.github.com/users/yaph",
        "html_url": "https://github.com/yaph",
        "followers_url": "https://api.github.com/users/yaph/followers",
        "following_url": "https://api.github.com/users/yaph/following{/other_user}",
        "gists_url": "https://api.github.com/users/yaph/gists{/gist_id}",
        "starred_url": "https://api.github.com/users/yaph/starred{/owner}{/repo}",
        "subscriptions_url": "https://api.github.com/users/yaph/subscriptions",
        "organizations_url": "https://api.github.com/users/yaph/orgs",
        "repos_url": "https://api.github.com/users/yaph/repos",
        "events_url": "https://api.github.com/users/yaph/events{/privacy}",
        "received_events_url": "https://api.github.com/users/yaph/received_events",
        "type": "User",
        "site_admin": false
      },
      "labels": [

      ],
      "state": "open",
      "locked": false,
      "assignee": null,
      "assignees": [

      ],
      "milestone": null,
      "comments": 0,
      "created_at": "2016-11-07T00:05:09Z",
      "updated_at": "2016-11-07T00:05:09Z",
      "closed_at": null,
      "author_association": "OWNER",
      "body": "Use multiprocessing in generate to read and write files\r\n\r\nhttps://docs.python.org/3/library/multiprocessing.html",
      "score": 1.0
    },
    {
      "url": "https://api.github.com/repos/yaph/geonamescache/issues/7",
      "repository_url": "https://api.github.com/repos/yaph/geonamescache",
      "labels_url": "https://api.github.com/repos/yaph/geonamescache/issues/7/labels{/name}",
      "comments_url": "https://api.github.com/repos/yaph/geonamescache/issues/7/comments",
      "events_url": "https://api.github.com/repos/yaph/geonamescache/issues/7/events",
      "html_url": "https://github.com/yaph/geonamescache/issues/7",
      "id": 45554263,
      "node_id": "MDU6SXNzdWU0NTU1NDI2Mw==",
      "number": 7,
      "title": "Call get_dataset_by_key with name of dataset, so there is no need for *_by_names methods",
      "user": {
        "login": "yaph",
        "id": 60051,
        "node_id": "MDQ6VXNlcjYwMDUx",
        "avatar_url": "https://avatars3.githubusercontent.com/u/60051?v=4",
        "gravatar_id": "",
        "url": "https://api.github.com/users/yaph",
        "html_url": "https://github.com/yaph",
        "followers_url": "https://api.github.com/users/yaph/followers",
        "following_url": "https://api.github.com/users/yaph/following{/other_user}",
        "gists_url": "https://api.github.com/users/yaph/gists{/gist_id}",
        "starred_url": "https://api.github.com/users/yaph/starred{/owner}{/repo}",
        "subscriptions_url": "https://api.github.com/users/yaph/subscriptions",
        "organizations_url": "https://api.github.com/users/yaph/orgs",
        "repos_url": "https://api.github.com/users/yaph/repos",
        "events_url": "https://api.github.com/users/yaph/events{/privacy}",
        "received_events_url": "https://api.github.com/users/yaph/received_events",
        "type": "User",
        "site_admin": false
      },
      "labels": [

      ],
      "state": "closed",
      "locked": false,
      "assignee": null,
      "assignees": [

      ],
      "milestone": null,
      "comments": 1,
      "created_at": "2014-10-11T15:35:01Z",
      "updated_at": "2016-09-25T21:14:35Z",
      "closed_at": "2016-09-25T21:14:35Z",
      "author_association": "OWNER",
      "body": "",
      "score": 1.0
    }
  ]
}
